invenio_documents/__init__.py
invenio_documents/api.py
invenio_documents/cli.py
invenio_documents/ext.py
invenio_documents/version.py
invenio_documents-1.0.0a1.dist-info/top_level.txt
invenio_documents-1.0.0a1.dist-info/entry_points.txt
invenio_documents-1.0.0a1.dist-info/METADATA
invenio_documents-1.0.0a1.dist-info/DESCRIPTION.rst
invenio_documents-1.0.0a1.dist-info/metadata.json
invenio_documents-1.0.0a1.dist-info/WHEEL
invenio_documents-1.0.0a1.dist-info/RECORD
