Metadata-Version: 2.0
Name: invenio-documents
Version: 1.0.0a1
Summary: Invenio module for document management.
Home-page: https://github.com/inveniosoftware/invenio-documents
Author: CERN
Author-email: info@invenio-software.org
License: GPLv2
Keywords: invenio documents
Platform: any
Classifier: Environment :: Web Environment
Classifier: Intended Audience :: Developers
Classifier: License :: OSI Approved :: GNU General Public License v2 (GPLv2)
Classifier: Operating System :: OS Independent
Classifier: Programming Language :: Python
Classifier: Topic :: Internet :: WWW/HTTP :: Dynamic Content
Classifier: Topic :: Software Development :: Libraries :: Python Modules
Classifier: Programming Language :: Python :: 2
Classifier: Programming Language :: Python :: 2.7
Classifier: Programming Language :: Python :: 3
Classifier: Programming Language :: Python :: 3.3
Classifier: Programming Language :: Python :: 3.4
Classifier: Programming Language :: Python :: 3.5
Classifier: Development Status :: 1 - Planning
Requires-Dist: Flask-BabelEx (>=0.9.2)
Requires-Dist: Flask-CLI (>=0.2.1)
Requires-Dist: fs (>=0.5.3)
Requires-Dist: invenio-records (>=1.0.0a4)
Requires-Dist: jsonpointer (>=1.9)
Requires-Dist: six (>=1.7.2)
Provides-Extra: all
Requires-Dist: Sphinx (>=1.3); extra == 'all'
Requires-Dist: check-manifest (>=0.25); extra == 'all'
Requires-Dist: coverage (>=4.0); extra == 'all'
Requires-Dist: isort (>=4.2.2); extra == 'all'
Requires-Dist: pep257 (>=0.7.0); extra == 'all'
Requires-Dist: pytest-cache (>=1.0); extra == 'all'
Requires-Dist: pytest-cov (>=1.8.0); extra == 'all'
Requires-Dist: pytest-pep8 (>=1.0.6); extra == 'all'
Requires-Dist: pytest (>=2.8.0); extra == 'all'
Requires-Dist: invenio-db[postgresql] (>=1.0.0a4); extra == 'all'
Requires-Dist: Sphinx (>=1.3); extra == 'all'
Requires-Dist: check-manifest (>=0.25); extra == 'all'
Requires-Dist: coverage (>=4.0); extra == 'all'
Requires-Dist: isort (>=4.2.2); extra == 'all'
Requires-Dist: pep257 (>=0.7.0); extra == 'all'
Requires-Dist: pytest-cache (>=1.0); extra == 'all'
Requires-Dist: pytest-cov (>=1.8.0); extra == 'all'
Requires-Dist: pytest-pep8 (>=1.0.6); extra == 'all'
Requires-Dist: pytest (>=2.8.0); extra == 'all'
Requires-Dist: invenio-db[postgresql] (>=1.0.0a4); extra == 'all'
Requires-Dist: invenio-db[mysql] (>=1.0.0a4); extra == 'all'
Provides-Extra: docs
Requires-Dist: Sphinx (>=1.3); extra == 'docs'
Provides-Extra: mysql
Requires-Dist: invenio-db[mysql] (>=1.0.0a4); extra == 'mysql'
Provides-Extra: postgresql
Requires-Dist: invenio-db[postgresql] (>=1.0.0a4); extra == 'postgresql'
Provides-Extra: tests
Requires-Dist: check-manifest (>=0.25); extra == 'tests'
Requires-Dist: coverage (>=4.0); extra == 'tests'
Requires-Dist: isort (>=4.2.2); extra == 'tests'
Requires-Dist: pep257 (>=0.7.0); extra == 'tests'
Requires-Dist: pytest-cache (>=1.0); extra == 'tests'
Requires-Dist: pytest-cov (>=1.8.0); extra == 'tests'
Requires-Dist: pytest-pep8 (>=1.0.6); extra == 'tests'
Requires-Dist: pytest (>=2.8.0); extra == 'tests'
